{
  "pizzas": [
    {
      "id": "5864cba4-211b-4024-ae89-44bba02eb266",
      "pizzaName": "veniam",
      "pizzaPrice": 12,
      "ingredients": [
        {
          "name": "maiores",
          "amount": 806,
          "id": 58
        },
        {
          "name": "et",
          "amount": 134,
          "id": 50
        },
        {
          "name": "qui",
          "amount": 312,
          "id": 62
        },
        {
          "name": "recusandae",
          "amount": 226,
          "id": 78
        }
      ],
      "allergens": [
        {
          "name": "reiciendis",
          "code": 79
        },
        {
          "name": "et",
          "code": 36
        },
        {
          "name": "corporis",
          "code": 75
        },
        {
          "name": "corporis",
          "code": 75
        },
        {
          "name": "quia",
          "code": 63
        }
      ]
    },
    {
      "id": "787f7db5-e1e6-4ac0-a9ba-546b85870eaf",
      "pizzaName": "sed",
      "pizzaPrice": 40,
      "ingredients": [
        {
          "name": "et",
          "amount": 319,
          "id": 20
        },
        {
          "name": "repellendus",
          "amount": 218,
          "id": 1
        },
        {
          "name": "corrupti",
          "amount": 469,
          "id": 92
        },
        {
          "name": "aut",
          "amount": 816,
          "id": 99
        }
      ],
      "allergens": [
        {
          "name": "aut",
          "code": 19
        },
        {
          "name": "earum",
          "code": 2
        }
      ]
    },
    {
      "id": "c469d587-4891-4aad-8fc4-9936f4dab249",
      "pizzaName": "ut",
      "pizzaPrice": 35,
      "ingredients": [
        {
          "name": "debitis",
          "amount": 346,
          "id": 2
        },
        {
          "name": "aut",
          "amount": 162,
          "id": 23
        },
        {
          "name": "vel",
          "amount": 124,
          "id": 43
        },
        {
          "name": "occaecati",
          "amount": 289,
          "id": 55
        },
        {
          "name": "earum",
          "amount": 767,
          "id": 51
        },
        {
          "name": "voluptatem",
          "amount": 213,
          "id": 40
        }
      ],
      "allergens": [
        {
          "name": "in",
          "code": 12
        },
        {
          "name": "repellat",
          "code": 47
        },
        {
          "name": "laborum",
          "code": 3
        },
        {
          "name": "odit",
          "code": 56
        }
      ]
    },
    {
      "id": "ad95f640-a875-4d9a-bea6-ec92e87491e5",
      "pizzaName": "laboriosam",
      "pizzaPrice": 28,
      "ingredients": [
        {
          "name": "velit",
          "amount": 133,
          "id": 38
        },
        {
          "name": "repellendus",
          "amount": 218,
          "id": 1
        },
        {
          "name": "tempora",
          "amount": 761,
          "id": 21
        },
        {
          "name": "distinctio",
          "amount": 663,
          "id": 8
        }
      ],
      "allergens": [
        {
          "name": "accusamus",
          "code": 52
        },
        {
          "name": "cum",
          "code": 78
        },
        {
          "name": "quia",
          "code": 21
        },
        {
          "name": "laudantium",
          "code": 54
        }
      ]
    },
    {
      "id": "17cfcf7e-af04-4b57-b0dd-e2fb58936715",
      "pizzaName": "quia",
      "pizzaPrice": 47,
      "ingredients": [
        {
          "name": "rem",
          "amount": 878,
          "id": 9
        },
        {
          "name": "aliquam",
          "amount": 664,
          "id": 44
        }
      ],
      "allergens": [
        {
          "name": "eum",
          "code": 9
        },
        {
          "name": "corrupti",
          "code": 45
        }
      ]
    },
    {
      "id": "a498c1d2-8830-4733-a5cf-878e225089db",
      "pizzaName": "aut",
      "pizzaPrice": 18,
      "ingredients": [
        {
          "name": "qui",
          "amount": 312,
          "id": 62
        },
        {
          "name": "vel",
          "amount": 408,
          "id": 26
        },
        {
          "name": "sed",
          "amount": 458,
          "id": 49
        },
        {
          "name": "quae",
          "amount": 438,
          "id": 69
        }
      ],
      "allergens": [
        {
          "name": "iure",
          "code": 30
        },
        {
          "name": "non",
          "code": 90
        },
        {
          "name": "laudantium",
          "code": 72
        },
        {
          "name": "laudantium",
          "code": 89
        },
        {
          "name": "impedit",
          "code": 77
        }
      ]
    },
    {
      "id": "a94c8345-7aa8-48b7-b5d5-3e4d79f758cd",
      "pizzaName": "corporis",
      "pizzaPrice": 14,
      "ingredients": [
        {
          "name": "delectus",
          "amount": 156,
          "id": 32
        },
        {
          "name": "eos",
          "amount": 225,
          "id": 96
        },
        {
          "name": "voluptate",
          "amount": 619,
          "id": 53
        },
        {
          "name": "voluptatem",
          "amount": 213,
          "id": 40
        }
      ],
      "allergens": [
        {
          "name": "asperiores",
          "code": 92
        },
        {
          "name": "repudiandae",
          "code": 95
        }
      ]
    },
    {
      "id": "c3df58b8-69c1-40f6-9ef9-39a64fbf9aed",
      "pizzaName": "maiores",
      "pizzaPrice": 22,
      "ingredients": [
        {
          "name": "autem",
          "amount": 735,
          "id": 52
        },
        {
          "name": "omnis",
          "amount": 620,
          "id": 15
        }
      ],
      "allergens": [
        {
          "name": "et",
          "code": 66
        },
        {
          "name": "placeat",
          "code": 86
        },
        {
          "name": "sint",
          "code": 28
        },
        {
          "name": "velit",
          "code": 91
        },
        {
          "name": "reiciendis",
          "code": 79
        }
      ]
    },
    {
      "id": "ef7ac3e3-fa98-4f65-9c19-bfefc4254b0c",
      "pizzaName": "est",
      "pizzaPrice": 23,
      "ingredients": [
        {
          "name": "aliquam",
          "amount": 848,
          "id": 22
        },
        {
          "name": "qui",
          "amount": 198,
          "id": 28
        },
        {
          "name": "et",
          "amount": 341,
          "id": 60
        },
        {
          "name": "sint",
          "amount": 203,
          "id": 72
        }
      ],
      "allergens": [
        {
          "name": "earum",
          "code": 2
        },
        {
          "name": "exercitationem",
          "code": 71
        },
        {
          "name": "mollitia",
          "code": 40
        },
        {
          "name": "tempora",
          "code": 60
        }
      ]
    },
    {
      "id": "7a34202a-b97a-4502-89d3-bdbfc0a21e12",
      "pizzaName": "aliquam",
      "pizzaPrice": 19,
      "ingredients": [
        {
          "name": "dolorem",
          "amount": 656,
          "id": 74
        },
        {
          "name": "est",
          "amount": 897,
          "id": 67
        },
        {
          "name": "vel",
          "amount": 408,
          "id": 26
        },
        {
          "name": "eligendi",
          "amount": 239,
          "id": 36
        },
        {
          "name": "odio",
          "amount": 402,
          "id": 59
        }
      ],
      "allergens": [
        {
          "name": "est",
          "code": 42
        },
        {
          "name": "quam",
          "code": 17
        }
      ]
    },
    {
      "id": "e2d12bae-0ec4-4287-9451-1db8edb479de",
      "pizzaName": "quidem",
      "pizzaPrice": 41,
      "ingredients": [
        {
          "name": "vel",
          "amount": 369,
          "id": 12
        },
        {
          "name": "quae",
          "amount": 438,
          "id": 69
        },
        {
          "name": "autem",
          "amount": 826,
          "id": 84
        },
        {
          "name": "officiis",
          "amount": 207,
          "id": 47
        }
      ],
      "allergens": [
        {
          "name": "natus",
          "code": 49
        },
        {
          "name": "aut",
          "code": 70
        },
        {
          "name": "aut",
          "code": 87
        },
        {
          "name": "aut",
          "code": 44
        },
        {
          "name": "nesciunt",
          "code": 93
        },
        {
          "name": "repudiandae",
          "code": 95
        }
      ]
    },
    {
      "id": "69b854ce-72a7-4545-b637-20af24cf1bf0",
      "pizzaName": "consequatur",
      "pizzaPrice": 24,
      "ingredients": [
        {
          "name": "aut",
          "amount": 369,
          "id": 61
        },
        {
          "name": "facilis",
          "amount": 346,
          "id": 0
        },
        {
          "name": "aliquid",
          "amount": 723,
          "id": 37
        }
      ],
      "allergens": [
        {
          "name": "voluptatem",
          "code": 74
        },
        {
          "name": "accusamus",
          "code": 52
        }
      ]
    },
    {
      "id": "1e6a0b2e-3ac7-4a4e-871b-8f7d428fc828",
      "pizzaName": "qui",
      "pizzaPrice": 38,
      "ingredients": [
        {
          "name": "omnis",
          "amount": 620,
          "id": 15
        },
        {
          "name": "qui",
          "amount": 312,
          "id": 62
        },
        {
          "name": "error",
          "amount": 490,
          "id": 46
        }
      ],
      "allergens": [
        {
          "name": "est",
          "code": 42
        },
        {
          "name": "dicta",
          "code": 35
        },
        {
          "name": "necessitatibus",
          "code": 61
        },
        {
          "name": "facilis",
          "code": 97
        }
      ]
    },
    {
      "id": "b2147272-3461-4816-8ee5-e5d90e3557da",
      "pizzaName": "sed",
      "pizzaPrice": 22,
      "ingredients": [
        {
          "name": "nesciunt",
          "amount": 465,
          "id": 75
        },
        {
          "name": "recusandae",
          "amount": 226,
          "id": 78
        }
      ],
      "allergens": [
        {
          "name": "odit",
          "code": 64
        },
        {
          "name": "accusamus",
          "code": 52
        },
        {
          "name": "voluptatibus",
          "code": 33
        },
        {
          "name": "rem",
          "code": 29
        },
        {
          "name": "corporis",
          "code": 75
        }
      ]
    },
    {
      "id": "4dd258d5-0be5-4578-89a0-b9d800401151",
      "pizzaName": "ut",
      "pizzaPrice": 29,
      "ingredients": [
        {
          "name": "non",
          "amount": 401,
          "id": 64
        },
        {
          "name": "dolores",
          "amount": 229,
          "id": 90
        },
        {
          "name": "voluptatem",
          "amount": 944,
          "id": 97
        },
        {
          "name": "rerum",
          "amount": 803,
          "id": 24
        },
        {
          "name": "esse",
          "amount": 518,
          "id": 98
        },
        {
          "name": "aut",
          "amount": 162,
          "id": 23
        }
      ],
      "allergens": [
        {
          "name": "qui",
          "code": 14
        },
        {
          "name": "asperiores",
          "code": 92
        },
        {
          "name": "repudiandae",
          "code": 58
        }
      ]
    },
    {
      "id": "ef603cee-a67d-4368-8d48-eeebe638551f",
      "pizzaName": "numquam",
      "pizzaPrice": 20,
      "ingredients": [
        {
          "name": "cum",
          "amount": 152,
          "id": 7
        },
        {
          "name": "dolorem",
          "amount": 656,
          "id": 74
        },
        {
          "name": "alias",
          "amount": 903,
          "id": 27
        },
        {
          "name": "autem",
          "amount": 826,
          "id": 84
        }
      ],
      "allergens": [
        {
          "name": "expedita",
          "code": 10
        },
        {
          "name": "natus",
          "code": 49
        },
        {
          "name": "accusamus",
          "code": 52
        }
      ]
    },
    {
      "id": "f7cf30c9-909e-496b-9c0d-6ab0e84325a8",
      "pizzaName": "deleniti",
      "pizzaPrice": 24,
      "ingredients": [
        {
          "name": "harum",
          "amount": 997,
          "id": 63
        },
        {
          "name": "et",
          "amount": 319,
          "id": 20
        },
        {
          "name": "quidem",
          "amount": 813,
          "id": 91
        },
        {
          "name": "non",
          "amount": 401,
          "id": 64
        },
        {
          "name": "autem",
          "amount": 735,
          "id": 52
        }
      ],
      "allergens": [
        {
          "name": "expedita",
          "code": 10
        },
        {
          "name": "asperiores",
          "code": 92
        },
        {
          "name": "corrupti",
          "code": 45
        },
        {
          "name": "reiciendis",
          "code": 79
        }
      ]
    },
    {
      "id": "284ee8b7-3369-478f-a68d-1d564fd95cf2",
      "pizzaName": "magnam",
      "pizzaPrice": 23,
      "ingredients": [
        {
          "name": "rerum",
          "amount": 803,
          "id": 24
        },
        {
          "name": "vel",
          "amount": 124,
          "id": 43
        },
        {
          "name": "autem",
          "amount": 735,
          "id": 52
        }
      ],
      "allergens": [
        {
          "name": "earum",
          "code": 2
        },
        {
          "name": "occaecati",
          "code": 26
        }
      ]
    },
    {
      "id": "05e56304-e7e2-49e3-b870-ac021e961f0f",
      "pizzaName": "amet",
      "pizzaPrice": 24,
      "ingredients": [
        {
          "name": "est",
          "amount": 195,
          "id": 71
        },
        {
          "name": "recusandae",
          "amount": 226,
          "id": 78
        },
        {
          "name": "cum",
          "amount": 152,
          "id": 7
        },
        {
          "name": "aliquam",
          "amount": 664,
          "id": 44
        },
        {
          "name": "et",
          "amount": 319,
          "id": 20
        }
      ],
      "allergens": [
        {
          "name": "unde",
          "code": 1
        },
        {
          "name": "ipsam",
          "code": 96
        },
        {
          "name": "in",
          "code": 57
        },
        {
          "name": "cum",
          "code": 78
        }
      ]
    },
    {
      "id": "d7129974-1f86-4851-83cf-65926cb58330",
      "pizzaName": "natus",
      "pizzaPrice": 2,
      "ingredients": [
        {
          "name": "natus",
          "amount": 452,
          "id": 25
        },
        {
          "name": "qui",
          "amount": 567,
          "id": 45
        }
      ],
      "allergens": [
        {
          "name": "repudiandae",
          "code": 95
        },
        {
          "name": "dolore",
          "code": 38
        }
      ]
    },
    {
      "id": "4a6cb49e-4ae9-4bc1-9b64-77f4b3e85b40",
      "pizzaName": "enim",
      "pizzaPrice": 11,
      "ingredients": [
        {
          "name": "praesentium",
          "amount": 493,
          "id": 14
        },
        {
          "name": "recusandae",
          "amount": 252,
          "id": 54
        },
        {
          "name": "ut",
          "amount": 366,
          "id": 48
        },
        {
          "name": "delectus",
          "amount": 156,
          "id": 32
        }
      ],
      "allergens": [
        {
          "name": "laudantium",
          "code": 54
        },
        {
          "name": "dolorem",
          "code": 59
        },
        {
          "name": "dicta",
          "code": 35
        },
        {
          "name": "voluptatem",
          "code": 55
        }
      ]
    },
    {
      "id": "285a5bd0-be54-47b6-827c-92013e763b96",
      "pizzaName": "dolor",
      "pizzaPrice": 36,
      "ingredients": [
        {
          "name": "occaecati",
          "amount": 289,
          "id": 55
        },
        {
          "name": "earum",
          "amount": 767,
          "id": 51
        },
        {
          "name": "delectus",
          "amount": 156,
          "id": 32
        },
        {
          "name": "aliquam",
          "amount": 848,
          "id": 22
        }
      ],
      "allergens": [
        {
          "name": "eius",
          "code": 65
        },
        {
          "name": "sequi",
          "code": 98
        },
        {
          "name": "dolore",
          "code": 69
        }
      ]
    },
    {
      "id": "43c2befa-ba57-4ed8-bac7-d4226b3d6464",
      "pizzaName": "repudiandae",
      "pizzaPrice": 9,
      "ingredients": [
        {
          "name": "vel",
          "amount": 408,
          "id": 26
        },
        {
          "name": "earum",
          "amount": 895,
          "id": 66
        }
      ],
      "allergens": [
        {
          "name": "dolor",
          "code": 11
        },
        {
          "name": "quidem",
          "code": 20
        },
        {
          "name": "et",
          "code": 82
        }
      ]
    },
    {
      "id": "290c14ec-ceeb-465a-907d-e959edee4188",
      "pizzaName": "magni",
      "pizzaPrice": 28,
      "ingredients": [
        {
          "name": "sequi",
          "amount": 27,
          "id": 76
        },
        {
          "name": "vel",
          "amount": 124,
          "id": 43
        },
        {
          "name": "non",
          "amount": 516,
          "id": 80
        },
        {
          "name": "incidunt",
          "amount": 5,
          "id": 83
        }
      ],
      "allergens": [
        {
          "name": "tempora",
          "code": 60
        },
        {
          "name": "aut",
          "code": 19
        },
        {
          "name": "et",
          "code": 82
        }
      ]
    },
    {
      "id": "1552225a-d6f0-4eb8-ba26-dc33005fbf3a",
      "pizzaName": "vel",
      "pizzaPrice": 49,
      "ingredients": [
        {
          "name": "qui",
          "amount": 312,
          "id": 62
        },
        {
          "name": "est",
          "amount": 195,
          "id": 71
        },
        {
          "name": "incidunt",
          "amount": 5,
          "id": 83
        },
        {
          "name": "est",
          "amount": 534,
          "id": 42
        },
        {
          "name": "beatae",
          "amount": 662,
          "id": 29
        }
      ],
      "allergens": [
        {
          "name": "placeat",
          "code": 86
        },
        {
          "name": "laudantium",
          "code": 89
        }
      ]
    },
    {
      "id": "51d4c1cc-66ed-4d95-bc03-1bf118447bd5",
      "pizzaName": "aut",
      "pizzaPrice": 34,
      "ingredients": [
        {
          "name": "dolorem",
          "amount": 656,
          "id": 74
        },
        {
          "name": "dolorem",
          "amount": 656,
          "id": 74
        },
        {
          "name": "occaecati",
          "amount": 289,
          "id": 55
        }
      ],
      "allergens": [
        {
          "name": "impedit",
          "code": 77
        },
        {
          "name": "repudiandae",
          "code": 58
        },
        {
          "name": "aut",
          "code": 44
        },
        {
          "name": "rerum",
          "code": 53
        },
        {
          "name": "et",
          "code": 82
        },
        {
          "name": "velit",
          "code": 91
        }
      ]
    },
    {
      "id": "1f88a20e-f367-49d9-91c9-c0397d331c84",
      "pizzaName": "aut",
      "pizzaPrice": 5,
      "ingredients": [
        {
          "name": "aliquam",
          "amount": 664,
          "id": 44
        },
        {
          "name": "quidem",
          "amount": 514,
          "id": 93
        },
        {
          "name": "et",
          "amount": 341,
          "id": 60
        }
      ],
      "allergens": [
        {
          "name": "aut",
          "code": 70
        },
        {
          "name": "mollitia",
          "code": 40
        },
        {
          "name": "sint",
          "code": 83
        }
      ]
    },
    {
      "id": "713483e1-e064-44da-817c-9f4363d0867d",
      "pizzaName": "aut",
      "pizzaPrice": 50,
      "ingredients": [
        {
          "name": "corrupti",
          "amount": 469,
          "id": 92
        },
        {
          "name": "dicta",
          "amount": 594,
          "id": 73
        },
        {
          "name": "eligendi",
          "amount": 239,
          "id": 36
        },
        {
          "name": "voluptatum",
          "amount": 3,
          "id": 77
        }
      ],
      "allergens": [
        {
          "name": "dolore",
          "code": 69
        },
        {
          "name": "odit",
          "code": 56
        },
        {
          "name": "qui",
          "code": 85
        },
        {
          "name": "eum",
          "code": 9
        },
        {
          "name": "accusamus",
          "code": 52
        }
      ]
    },
    {
      "id": "cfb18fa7-9435-4e8e-88c6-fb07e9cb88fd",
      "pizzaName": "aliquam",
      "pizzaPrice": 26,
      "ingredients": [
        {
          "name": "sequi",
          "amount": 369,
          "id": 88
        },
        {
          "name": "aperiam",
          "amount": 690,
          "id": 39
        },
        {
          "name": "voluptate",
          "amount": 619,
          "id": 53
        }
      ],
      "allergens": [
        {
          "name": "repellat",
          "code": 47
        },
        {
          "name": "explicabo",
          "code": 5
        },
        {
          "name": "sint",
          "code": 28
        },
        {
          "name": "dolor",
          "code": 18
        }
      ]
    },
    {
      "id": "f6aedd98-faee-45f7-9445-68d2d834e441",
      "pizzaName": "sint",
      "pizzaPrice": 4,
      "ingredients": [
        {
          "name": "dolorem",
          "amount": 873,
          "id": 34
        },
        {
          "name": "non",
          "amount": 516,
          "id": 80
        },
        {
          "name": "aut",
          "amount": 816,
          "id": 99
        }
      ],
      "allergens": [
        {
          "name": "earum",
          "code": 2
        },
        {
          "name": "sint",
          "code": 28
        }
      ]
    },
    {
      "id": "e2b47a46-4c9b-4329-82d7-151d216f9116",
      "pizzaName": "optio",
      "pizzaPrice": 34,
      "ingredients": [
        {
          "name": "dicta",
          "amount": 594,
          "id": 73
        },
        {
          "name": "vel",
          "amount": 408,
          "id": 26
        },
        {
          "name": "repudiandae",
          "amount": 2,
          "id": 82
        },
        {
          "name": "et",
          "amount": 341,
          "id": 60
        }
      ],
      "allergens": [
        {
          "name": "qui",
          "code": 14
        },
        {
          "name": "cum",
          "code": 78
        },
        {
          "name": "tempora",
          "code": 60
        }
      ]
    },
    {
      "id": "278baebf-ad1e-438d-8871-24a7b050e355",
      "pizzaName": "voluptatem",
      "pizzaPrice": 9,
      "ingredients": [
        {
          "name": "error",
          "amount": 490,
          "id": 46
        },
        {
          "name": "harum",
          "amount": 997,
          "id": 63
        },
        {
          "name": "vel",
          "amount": 408,
          "id": 26
        },
        {
          "name": "et",
          "amount": 744,
          "id": 85
        }
      ],
      "allergens": [
        {
          "name": "et",
          "code": 82
        },
        {
          "name": "laudantium",
          "code": 89
        },
        {
          "name": "et",
          "code": 24
        }
      ]
    },
    {
      "id": "1a1cb920-5146-479e-b75d-c95683680da8",
      "pizzaName": "est",
      "pizzaPrice": 1,
      "ingredients": [
        {
          "name": "sequi",
          "amount": 369,
          "id": 88
        },
        {
          "name": "natus",
          "amount": 452,
          "id": 25
        },
        {
          "name": "natus",
          "amount": 452,
          "id": 25
        }
      ],
      "allergens": [
        {
          "name": "aut",
          "code": 70
        },
        {
          "name": "laborum",
          "code": 3
        },
        {
          "name": "rerum",
          "code": 53
        }
      ]
    },
    {
      "id": "de469fc3-e994-408f-a127-0be2332ece1f",
      "pizzaName": "molestiae",
      "pizzaPrice": 22,
      "ingredients": [
        {
          "name": "sequi",
          "amount": 27,
          "id": 76
        },
        {
          "name": "qui",
          "amount": 567,
          "id": 45
        },
        {
          "name": "recusandae",
          "amount": 252,
          "id": 54
        }
      ],
      "allergens": [
        {
          "name": "quam",
          "code": 17
        },
        {
          "name": "et",
          "code": 25
        },
        {
          "name": "aut",
          "code": 70
        }
      ]
    },
    {
      "id": "436ee28a-4bc6-4064-a91a-66ead389f401",
      "pizzaName": "aut",
      "pizzaPrice": 46,
      "ingredients": [
        {
          "name": "vel",
          "amount": 408,
          "id": 26
        },
        {
          "name": "ut",
          "amount": 366,
          "id": 48
        },
        {
          "name": "qui",
          "amount": 198,
          "id": 28
        }
      ],
      "allergens": [
        {
          "name": "reiciendis",
          "code": 79
        },
        {
          "name": "non",
          "code": 73
        },
        {
          "name": "placeat",
          "code": 86
        },
        {
          "name": "qui",
          "code": 85
        }
      ]
    },
    {
      "id": "781b2e53-2243-4274-9690-56ca09d3d498",
      "pizzaName": "pariatur",
      "pizzaPrice": 29,
      "ingredients": [
        {
          "name": "debitis",
          "amount": 346,
          "id": 2
        },
        {
          "name": "harum",
          "amount": 997,
          "id": 63
        },
        {
          "name": "autem",
          "amount": 735,
          "id": 52
        },
        {
          "name": "sint",
          "amount": 310,
          "id": 4
        }
      ],
      "allergens": [
        {
          "name": "quidem",
          "code": 20
        },
        {
          "name": "aut",
          "code": 70
        },
        {
          "name": "odit",
          "code": 64
        }
      ]
    },
    {
      "id": "205f959b-e366-4923-9e23-1d5e34815f02",
      "pizzaName": "id",
      "pizzaPrice": 8,
      "ingredients": [
        {
          "name": "non",
          "amount": 178,
          "id": 35
        },
        {
          "name": "odio",
          "amount": 402,
          "id": 59
        },
        {
          "name": "delectus",
          "amount": 156,
          "id": 32
        },
        {
          "name": "aut",
          "amount": 816,
          "id": 99
        }
      ],
      "allergens": [
        {
          "name": "aut",
          "code": 70
        },
        {
          "name": "non",
          "code": 73
        }
      ]
    },
    {
      "id": "08a32206-8665-4f84-a9ad-bc694589f5f7",
      "pizzaName": "voluptas",
      "pizzaPrice": 37,
      "ingredients": [
        {
          "name": "est",
          "amount": 195,
          "id": 71
        },
        {
          "name": "asperiores",
          "amount": 12,
          "id": 18
        },
        {
          "name": "aperiam",
          "amount": 690,
          "id": 39
        }
      ],
      "allergens": [
        {
          "name": "eius",
          "code": 65
        },
        {
          "name": "repellat",
          "code": 47
        },
        {
          "name": "quidem",
          "code": 20
        },
        {
          "name": "qui",
          "code": 85
        }
      ]
    },
    {
      "id": "1de32868-cc6b-414f-9e5a-a105c8f79ae6",
      "pizzaName": "est",
      "pizzaPrice": 49,
      "ingredients": [
        {
          "name": "autem",
          "amount": 669,
          "id": 89
        },
        {
          "name": "voluptate",
          "amount": 619,
          "id": 53
        }
      ],
      "allergens": [
        {
          "name": "eum",
          "code": 16
        },
        {
          "name": "rerum",
          "code": 53
        },
        {
          "name": "et",
          "code": 24
        }
      ]
    },
    {
      "id": "7a32d4be-6b35-4deb-9674-7cd9d775167b",
      "pizzaName": "quibusdam",
      "pizzaPrice": 36,
      "ingredients": [
        {
          "name": "autem",
          "amount": 669,
          "id": 89
        },
        {
          "name": "eaque",
          "amount": 291,
          "id": 81
        },
        {
          "name": "ex",
          "amount": 405,
          "id": 94
        }
      ],
      "allergens": [
        {
          "name": "est",
          "code": 42
        },
        {
          "name": "voluptatibus",
          "code": 33
        },
        {
          "name": "eum",
          "code": 16
        }
      ]
    },
    {
      "id": "9be11887-0ebd-4f55-9726-35adc90fd04a",
      "pizzaName": "assumenda",
      "pizzaPrice": 9,
      "ingredients": [
        {
          "name": "voluptate",
          "amount": 619,
          "id": 53
        },
        {
          "name": "magnam",
          "amount": 184,
          "id": 31
        },
        {
          "name": "distinctio",
          "amount": 663,
          "id": 8
        },
        {
          "name": "delectus",
          "amount": 156,
          "id": 32
        },
        {
          "name": "voluptate",
          "amount": 619,
          "id": 53
        },
        {
          "name": "qui",
          "amount": 567,
          "id": 45
        }
      ],
      "allergens": [
        {
          "name": "nam",
          "code": 41
        },
        {
          "name": "aut",
          "code": 19
        },
        {
          "name": "accusamus",
          "code": 52
        }
      ]
    },
    {
      "id": "6291ca41-9e1d-4776-b968-9bc9252bb0eb",
      "pizzaName": "aut",
      "pizzaPrice": 28,
      "ingredients": [
        {
          "name": "est",
          "amount": 897,
          "id": 67
        },
        {
          "name": "voluptatem",
          "amount": 14,
          "id": 87
        },
        {
          "name": "consequatur",
          "amount": 850,
          "id": 95
        }
      ],
      "allergens": [
        {
          "name": "error",
          "code": 46
        },
        {
          "name": "aut",
          "code": 87
        },
        {
          "name": "exercitationem",
          "code": 6
        },
        {
          "name": "iure",
          "code": 30
        }
      ]
    },
    {
      "id": "a2c426db-1b94-44ae-b304-910e965fbebd",
      "pizzaName": "unde",
      "pizzaPrice": 14,
      "ingredients": [
        {
          "name": "non",
          "amount": 401,
          "id": 64
        },
        {
          "name": "magnam",
          "amount": 184,
          "id": 31
        },
        {
          "name": "tempora",
          "amount": 761,
          "id": 21
        }
      ],
      "allergens": [
        {
          "name": "eius",
          "code": 65
        },
        {
          "name": "asperiores",
          "code": 92
        },
        {
          "name": "dolor",
          "code": 18
        },
        {
          "name": "officiis",
          "code": 39
        }
      ]
    },
    {
      "id": "81070592-8b38-4ff5-8cc2-cda88f824c38",
      "pizzaName": "quidem",
      "pizzaPrice": 11,
      "ingredients": [
        {
          "name": "incidunt",
          "amount": 5,
          "id": 83
        },
        {
          "name": "tempora",
          "amount": 761,
          "id": 21
        },
        {
          "name": "et",
          "amount": 319,
          "id": 20
        }
      ],
      "allergens": [
        {
          "name": "error",
          "code": 46
        },
        {
          "name": "corrupti",
          "code": 45
        },
        {
          "name": "animi",
          "code": 32
        },
        {
          "name": "saepe",
          "code": 22
        }
      ]
    },
    {
      "id": "6e4feee4-a7ef-4381-87cd-005aa2f453bb",
      "pizzaName": "adipisci",
      "pizzaPrice": 47,
      "ingredients": [
        {
          "name": "sequi",
          "amount": 369,
          "id": 88
        },
        {
          "name": "qui",
          "amount": 198,
          "id": 28
        },
        {
          "name": "vel",
          "amount": 124,
          "id": 43
        },
        {
          "name": "dolorem",
          "amount": 873,
          "id": 34
        },
        {
          "name": "eligendi",
          "amount": 239,
          "id": 36
        }
      ],
      "allergens": [
        {
          "name": "dolore",
          "code": 69
        },
        {
          "name": "qui",
          "code": 14
        },
        {
          "name": "eum",
          "code": 16
        },
        {
          "name": "aut",
          "code": 68
        }
      ]
    },
    {
      "id": "f7c547ff-d267-48be-9529-17a40c8d1b0d",
      "pizzaName": "quia",
      "pizzaPrice": 8,
      "ingredients": [
        {
          "name": "earum",
          "amount": 895,
          "id": 66
        },
        {
          "name": "magnam",
          "amount": 184,
          "id": 31
        }
      ],
      "allergens": [
        {
          "name": "repellendus",
          "code": 43
        },
        {
          "name": "animi",
          "code": 32
        },
        {
          "name": "quam",
          "code": 17
        }
      ]
    },
    {
      "id": "c0700998-40c6-4ce7-b8d2-0bac773814af",
      "pizzaName": "laboriosam",
      "pizzaPrice": 30,
      "ingredients": [
        {
          "name": "tempora",
          "amount": 761,
          "id": 21
        },
        {
          "name": "non",
          "amount": 401,
          "id": 64
        },
        {
          "name": "beatae",
          "amount": 662,
          "id": 29
        },
        {
          "name": "nam",
          "amount": 557,
          "id": 11
        },
        {
          "name": "consequatur",
          "amount": 850,
          "id": 95
        },
        {
          "name": "ex",
          "amount": 405,
          "id": 94
        }
      ],
      "allergens": [
        {
          "name": "non",
          "code": 73
        },
        {
          "name": "eum",
          "code": 9
        },
        {
          "name": "corrupti",
          "code": 45
        }
      ]
    },
    {
      "id": "57b3df3b-7123-4dd6-a169-b87347acfb38",
      "pizzaName": "in",
      "pizzaPrice": 11,
      "ingredients": [
        {
          "name": "vel",
          "amount": 408,
          "id": 26
        },
        {
          "name": "consequatur",
          "amount": 850,
          "id": 95
        }
      ],
      "allergens": [
        {
          "name": "officiis",
          "code": 39
        },
        {
          "name": "et",
          "code": 82
        },
        {
          "name": "odit",
          "code": 56
        },
        {
          "name": "occaecati",
          "code": 26
        },
        {
          "name": "ipsa",
          "code": 15
        }
      ]
    },
    {
      "id": "d6a7403a-260e-4217-9a45-d6d2dc135499",
      "pizzaName": "a",
      "pizzaPrice": 30,
      "ingredients": [
        {
          "name": "deserunt",
          "amount": 823,
          "id": 6
        },
        {
          "name": "autem",
          "amount": 669,
          "id": 89
        },
        {
          "name": "occaecati",
          "amount": 289,
          "id": 55
        },
        {
          "name": "aliquam",
          "amount": 664,
          "id": 44
        }
      ],
      "allergens": [
        {
          "name": "repudiandae",
          "code": 95
        },
        {
          "name": "et",
          "code": 80
        },
        {
          "name": "impedit",
          "code": 77
        }
      ]
    },
    {
      "id": "aa0e9f0d-473e-4cf9-8646-643a752a691a",
      "pizzaName": "non",
      "pizzaPrice": 14,
      "ingredients": [
        {
          "name": "ut",
          "amount": 366,
          "id": 48
        },
        {
          "name": "eos",
          "amount": 225,
          "id": 96
        },
        {
          "name": "officia",
          "amount": 251,
          "id": 33
        }
      ],
      "allergens": [
        {
          "name": "sint",
          "code": 83
        },
        {
          "name": "quia",
          "code": 21
        },
        {
          "name": "expedita",
          "code": 10
        },
        {
          "name": "ratione",
          "code": 51
        },
        {
          "name": "sit",
          "code": 84
        }
      ]
    },
    {
      "id": "4a82bec8-ca9e-4da4-9604-113491a0b462",
      "pizzaName": "laudantium",
      "pizzaPrice": 10,
      "ingredients": [
        {
          "name": "aperiam",
          "amount": 690,
          "id": 39
        },
        {
          "name": "non",
          "amount": 401,
          "id": 64
        }
      ],
      "allergens": [
        {
          "name": "animi",
          "code": 0
        },
        {
          "name": "exercitationem",
          "code": 71
        },
        {
          "name": "rem",
          "code": 29
        }
      ]
    },
    {
      "id": "2521f04c-adf2-434a-9143-11d78d063369",
      "pizzaName": "enim",
      "pizzaPrice": 11,
      "ingredients": [
        {
          "name": "distinctio",
          "amount": 663,
          "id": 8
        },
        {
          "name": "voluptate",
          "amount": 619,
          "id": 53
        },
        {
          "name": "repudiandae",
          "amount": 2,
          "id": 82
        },
        {
          "name": "corporis",
          "amount": 374,
          "id": 17
        }
      ],
      "allergens": [
        {
          "name": "qui",
          "code": 85
        },
        {
          "name": "accusamus",
          "code": 52
        },
        {
          "name": "occaecati",
          "code": 26
        },
        {
          "name": "fugiat",
          "code": 27
        }
      ]
    },
    {
      "id": "e0933fe8-196b-49b8-b292-57ffeefe26c4",
      "pizzaName": "non",
      "pizzaPrice": 33,
      "ingredients": [
        {
          "name": "aut",
          "amount": 162,
          "id": 23
        },
        {
          "name": "neque",
          "amount": 417,
          "id": 5
        }
      ],
      "allergens": [
        {
          "name": "asperiores",
          "code": 92
        },
        {
          "name": "ut",
          "code": 76
        },
        {
          "name": "voluptatibus",
          "code": 33
        }
      ]
    },
    {
      "id": "ee8d8cac-2748-4655-8037-330a99fb2b45",
      "pizzaName": "ut",
      "pizzaPrice": 32,
      "ingredients": [
        {
          "name": "officiis",
          "amount": 207,
          "id": 47
        },
        {
          "name": "quidem",
          "amount": 813,
          "id": 91
        }
      ],
      "allergens": [
        {
          "name": "aut",
          "code": 87
        },
        {
          "name": "laudantium",
          "code": 89
        },
        {
          "name": "facere",
          "code": 34
        },
        {
          "name": "mollitia",
          "code": 40
        },
        {
          "name": "velit",
          "code": 91
        }
      ]
    },
    {
      "id": "156e14cb-12ff-4337-816e-e60e1bc2ed98",
      "pizzaName": "dignissimos",
      "pizzaPrice": 17,
      "ingredients": [
        {
          "name": "officiis",
          "amount": 207,
          "id": 47
        },
        {
          "name": "ex",
          "amount": 405,
          "id": 94
        },
        {
          "name": "et",
          "amount": 744,
          "id": 85
        }
      ],
      "allergens": [
        {
          "name": "aut",
          "code": 68
        },
        {
          "name": "laborum",
          "code": 3
        },
        {
          "name": "dolor",
          "code": 11
        }
      ]
    },
    {
      "id": "612ecea5-53eb-4519-8a8b-d8785084b94c",
      "pizzaName": "sint",
      "pizzaPrice": 28,
      "ingredients": [
        {
          "name": "earum",
          "amount": 767,
          "id": 51
        },
        {
          "name": "accusamus",
          "amount": 169,
          "id": 3
        }
      ],
      "allergens": [
        {
          "name": "repudiandae",
          "code": 95
        },
        {
          "name": "sit",
          "code": 84
        }
      ]
    },
    {
      "id": "a5a5e171-2720-49a5-9882-acd8df794069",
      "pizzaName": "facilis",
      "pizzaPrice": 43,
      "ingredients": [
        {
          "name": "qui",
          "amount": 567,
          "id": 45
        },
        {
          "name": "autem",
          "amount": 735,
          "id": 52
        },
        {
          "name": "earum",
          "amount": 895,
          "id": 66
        },
        {
          "name": "et",
          "amount": 319,
          "id": 20
        },
        {
          "name": "officia",
          "amount": 251,
          "id": 33
        },
        {
          "name": "repellendus",
          "amount": 218,
          "id": 1
        }
      ],
      "allergens": [
        {
          "name": "sint",
          "code": 83
        },
        {
          "name": "expedita",
          "code": 10
        },
        {
          "name": "dolor",
          "code": 18
        },
        {
          "name": "sequi",
          "code": 98
        }
      ]
    },
    {
      "id": "e4bc1582-179b-4ea6-92d7-b2481501ae59",
      "pizzaName": "expedita",
      "pizzaPrice": 1,
      "ingredients": [
        {
          "name": "est",
          "amount": 195,
          "id": 71
        },
        {
          "name": "nam",
          "amount": 557,
          "id": 11
        },
        {
          "name": "odio",
          "amount": 402,
          "id": 59
        }
      ],
      "allergens": [
        {
          "name": "in",
          "code": 12
        },
        {
          "name": "dolore",
          "code": 48
        },
        {
          "name": "repudiandae",
          "code": 95
        },
        {
          "name": "sint",
          "code": 83
        }
      ]
    },
    {
      "id": "dcb5ff2c-07d3-43cc-87d7-9ed5f06cc470",
      "pizzaName": "sit",
      "pizzaPrice": 39,
      "ingredients": [
        {
          "name": "dicta",
          "amount": 594,
          "id": 73
        },
        {
          "name": "ex",
          "amount": 405,
          "id": 94
        },
        {
          "name": "repudiandae",
          "amount": 2,
          "id": 82
        },
        {
          "name": "harum",
          "amount": 997,
          "id": 63
        },
        {
          "name": "nam",
          "amount": 557,
          "id": 11
        }
      ],
      "allergens": [
        {
          "name": "est",
          "code": 42
        },
        {
          "name": "accusamus",
          "code": 52
        },
        {
          "name": "fugiat",
          "code": 27
        },
        {
          "name": "et",
          "code": 80
        }
      ]
    },
    {
      "id": "60751fec-85df-4f2a-b208-1719568b188a",
      "pizzaName": "ipsa",
      "pizzaPrice": 7,
      "ingredients": [
        {
          "name": "omnis",
          "amount": 620,
          "id": 15
        },
        {
          "name": "officia",
          "amount": 251,
          "id": 33
        },
        {
          "name": "aliquam",
          "amount": 664,
          "id": 44
        }
      ],
      "allergens": [
        {
          "name": "non",
          "code": 90
        },
        {
          "name": "eius",
          "code": 65
        },
        {
          "name": "aliquam",
          "code": 4
        },
        {
          "name": "repellat",
          "code": 47
        },
        {
          "name": "occaecati",
          "code": 26
        }
      ]
    },
    {
      "id": "e5d2d20f-8983-4445-bb19-fc8f3dd8cb32",
      "pizzaName": "qui",
      "pizzaPrice": 2,
      "ingredients": [
        {
          "name": "recusandae",
          "amount": 252,
          "id": 54
        },
        {
          "name": "sint",
          "amount": 310,
          "id": 4
        },
        {
          "name": "autem",
          "amount": 669,
          "id": 89
        },
        {
          "name": "recusandae",
          "amount": 226,
          "id": 78
        }
      ],
      "allergens": [
        {
          "name": "saepe",
          "code": 22
        },
        {
          "name": "repellendus",
          "code": 43
        },
        {
          "name": "omnis",
          "code": 62
        },
        {
          "name": "tempora",
          "code": 60
        },
        {
          "name": "dicta",
          "code": 35
        },
        {
          "name": "impedit",
          "code": 77
        }
      ]
    },
    {
      "id": "e45283de-35a2-4057-9965-4ca4f14b0f05",
      "pizzaName": "non",
      "pizzaPrice": 37,
      "ingredients": [
        {
          "name": "repellendus",
          "amount": 868,
          "id": 56
        },
        {
          "name": "aliquam",
          "amount": 848,
          "id": 22
        },
        {
          "name": "maiores",
          "amount": 806,
          "id": 58
        }
      ],
      "allergens": [
        {
          "name": "dolore",
          "code": 69
        },
        {
          "name": "explicabo",
          "code": 5
        },
        {
          "name": "sint",
          "code": 83
        },
        {
          "name": "rerum",
          "code": 8
        },
        {
          "name": "non",
          "code": 73
        }
      ]
    },
    {
      "id": "a1c4e905-6570-4f2f-a0e7-8d1d4cb944ae",
      "pizzaName": "sed",
      "pizzaPrice": 49,
      "ingredients": [
        {
          "name": "est",
          "amount": 195,
          "id": 71
        },
        {
          "name": "quae",
          "amount": 438,
          "id": 69
        }
      ],
      "allergens": [
        {
          "name": "natus",
          "code": 49
        },
        {
          "name": "impedit",
          "code": 77
        },
        {
          "name": "natus",
          "code": 49
        }
      ]
    },
    {
      "id": "5549b1f6-2617-4b5f-bf5a-d1bc1f07ce6f",
      "pizzaName": "eos",
      "pizzaPrice": 38,
      "ingredients": [
        {
          "name": "asperiores",
          "amount": 12,
          "id": 18
        },
        {
          "name": "vel",
          "amount": 124,
          "id": 43
        },
        {
          "name": "asperiores",
          "amount": 12,
          "id": 18
        },
        {
          "name": "voluptatum",
          "amount": 3,
          "id": 77
        },
        {
          "name": "qui",
          "amount": 486,
          "id": 79
        }
      ],
      "allergens": [
        {
          "name": "animi",
          "code": 0
        },
        {
          "name": "dolore",
          "code": 88
        },
        {
          "name": "tempore",
          "code": 31
        },
        {
          "name": "aperiam",
          "code": 99
        },
        {
          "name": "dolorem",
          "code": 59
        }
      ]
    },
    {
      "id": "55c5eed7-578e-46b5-b12f-db11ec206110",
      "pizzaName": "voluptates",
      "pizzaPrice": 28,
      "ingredients": [
        {
          "name": "rem",
          "amount": 878,
          "id": 9
        },
        {
          "name": "facilis",
          "amount": 346,
          "id": 0
        },
        {
          "name": "aut",
          "amount": 816,
          "id": 99
        },
        {
          "name": "incidunt",
          "amount": 5,
          "id": 83
        }
      ],
      "allergens": [
        {
          "name": "ut",
          "code": 76
        },
        {
          "name": "officiis",
          "code": 39
        },
        {
          "name": "odit",
          "code": 64
        },
        {
          "name": "ipsam",
          "code": 96
        },
        {
          "name": "facere",
          "code": 34
        }
      ]
    },
    {
      "id": "2b4db24d-024d-4da4-bbdc-55bda41f2645",
      "pizzaName": "quo",
      "pizzaPrice": 4,
      "ingredients": [
        {
          "name": "qui",
          "amount": 567,
          "id": 45
        },
        {
          "name": "est",
          "amount": 195,
          "id": 71
        },
        {
          "name": "est",
          "amount": 195,
          "id": 71
        }
      ],
      "allergens": [
        {
          "name": "dolorem",
          "code": 59
        },
        {
          "name": "dicta",
          "code": 35
        },
        {
          "name": "eum",
          "code": 16
        },
        {
          "name": "eum",
          "code": 23
        }
      ]
    },
    {
      "id": "2b45cb3a-8b60-4019-a0e9-ccd7654571ff",
      "pizzaName": "tempora",
      "pizzaPrice": 13,
      "ingredients": [
        {
          "name": "vel",
          "amount": 124,
          "id": 43
        },
        {
          "name": "qui",
          "amount": 486,
          "id": 79
        },
        {
          "name": "aut",
          "amount": 162,
          "id": 23
        }
      ],
      "allergens": [
        {
          "name": "cum",
          "code": 78
        },
        {
          "name": "rem",
          "code": 29
        },
        {
          "name": "rerum",
          "code": 67
        }
      ]
    },
    {
      "id": "bd4e7040-df3c-4d20-b2ec-07fd724da514",
      "pizzaName": "iusto",
      "pizzaPrice": 37,
      "ingredients": [
        {
          "name": "repellendus",
          "amount": 868,
          "id": 56
        },
        {
          "name": "alias",
          "amount": 903,
          "id": 27
        },
        {
          "name": "corporis",
          "amount": 374,
          "id": 17
        },
        {
          "name": "non",
          "amount": 516,
          "id": 80
        },
        {
          "name": "non",
          "amount": 178,
          "id": 35
        },
        {
          "name": "maiores",
          "amount": 164,
          "id": 16
        }
      ],
      "allergens": [
        {
          "name": "iure",
          "code": 30
        },
        {
          "name": "rerum",
          "code": 8
        },
        {
          "name": "nam",
          "code": 41
        },
        {
          "name": "aut",
          "code": 70
        },
        {
          "name": "velit",
          "code": 37
        },
        {
          "name": "voluptatem",
          "code": 55
        }
      ]
    },
    {
      "id": "9e033962-03e1-44a1-a401-44499a37e27f",
      "pizzaName": "asperiores",
      "pizzaPrice": 37,
      "ingredients": [
        {
          "name": "autem",
          "amount": 669,
          "id": 89
        },
        {
          "name": "vel",
          "amount": 408,
          "id": 26
        },
        {
          "name": "alias",
          "amount": 903,
          "id": 27
        }
      ],
      "allergens": [
        {
          "name": "aut",
          "code": 19
        },
        {
          "name": "deleniti",
          "code": 7
        },
        {
          "name": "eius",
          "code": 65
        }
      ]
    },
    {
      "id": "e0957d0e-ccd6-4e0a-b2c1-fb771773e65e",
      "pizzaName": "autem",
      "pizzaPrice": 44,
      "ingredients": [
        {
          "name": "dolorem",
          "amount": 656,
          "id": 74
        },
        {
          "name": "est",
          "amount": 195,
          "id": 71
        },
        {
          "name": "asperiores",
          "amount": 12,
          "id": 18
        },
        {
          "name": "et",
          "amount": 134,
          "id": 50
        },
        {
          "name": "est",
          "amount": 534,
          "id": 42
        },
        {
          "name": "rerum",
          "amount": 803,
          "id": 24
        }
      ],
      "allergens": [
        {
          "name": "dolor",
          "code": 11
        },
        {
          "name": "velit",
          "code": 37
        },
        {
          "name": "nesciunt",
          "code": 93
        }
      ]
    },
    {
      "id": "41cc23be-b67a-4376-a004-11d2943d2c84",
      "pizzaName": "tenetur",
      "pizzaPrice": 50,
      "ingredients": [
        {
          "name": "asperiores",
          "amount": 12,
          "id": 18
        },
        {
          "name": "rem",
          "amount": 878,
          "id": 9
        },
        {
          "name": "repellendus",
          "amount": 218,
          "id": 1
        },
        {
          "name": "corrupti",
          "amount": 469,
          "id": 92
        },
        {
          "name": "qui",
          "amount": 486,
          "id": 79
        }
      ],
      "allergens": [
        {
          "name": "ut",
          "code": 76
        },
        {
          "name": "aut",
          "code": 19
        },
        {
          "name": "sequi",
          "code": 98
        },
        {
          "name": "dolorem",
          "code": 59
        }
      ]
    },
    {
      "id": "0bf43832-67aa-45c5-b7af-ddc5da9f4e9f",
      "pizzaName": "odio",
      "pizzaPrice": 16,
      "ingredients": [
        {
          "name": "voluptatum",
          "amount": 3,
          "id": 77
        },
        {
          "name": "cum",
          "amount": 152,
          "id": 7
        },
        {
          "name": "vel",
          "amount": 408,
          "id": 26
        }
      ],
      "allergens": [
        {
          "name": "non",
          "code": 73
        },
        {
          "name": "sint",
          "code": 83
        }
      ]
    },
    {
      "id": "ae2ff493-0fcc-4a6d-89cd-856c1cfdfda3",
      "pizzaName": "nam",
      "pizzaPrice": 17,
      "ingredients": [
        {
          "name": "tenetur",
          "amount": 248,
          "id": 70
        },
        {
          "name": "aperiam",
          "amount": 690,
          "id": 39
        },
        {
          "name": "est",
          "amount": 534,
          "id": 42
        },
        {
          "name": "recusandae",
          "amount": 252,
          "id": 54
        }
      ],
      "allergens": [
        {
          "name": "reiciendis",
          "code": 79
        },
        {
          "name": "tempora",
          "code": 60
        },
        {
          "name": "repudiandae",
          "code": 95
        }
      ]
    },
    {
      "id": "1086b45d-cf74-452d-8bcc-d916c02dcd11",
      "pizzaName": "est",
      "pizzaPrice": 47,
      "ingredients": [
        {
          "name": "dolores",
          "amount": 229,
          "id": 90
        },
        {
          "name": "tempora",
          "amount": 761,
          "id": 21
        },
        {
          "name": "sint",
          "amount": 310,
          "id": 4
        },
        {
          "name": "voluptatum",
          "amount": 3,
          "id": 77
        },
        {
          "name": "aut",
          "amount": 816,
          "id": 99
        }
      ],
      "allergens": [
        {
          "name": "aut",
          "code": 70
        },
        {
          "name": "quia",
          "code": 21
        },
        {
          "name": "repellendus",
          "code": 43
        }
      ]
    },
    {
      "id": "ba31befd-20a2-4646-8032-2ef669de5dc7",
      "pizzaName": "rerum",
      "pizzaPrice": 21,
      "ingredients": [
        {
          "name": "est",
          "amount": 952,
          "id": 57
        },
        {
          "name": "odio",
          "amount": 402,
          "id": 59
        },
        {
          "name": "voluptatem",
          "amount": 944,
          "id": 97
        },
        {
          "name": "voluptatem",
          "amount": 944,
          "id": 97
        }
      ],
      "allergens": [
        {
          "name": "ipsam",
          "code": 96
        },
        {
          "name": "ipsam",
          "code": 96
        }
      ]
    },
    {
      "id": "a64aa865-ee4f-447e-b4de-4d96ee51ea32",
      "pizzaName": "maiores",
      "pizzaPrice": 1,
      "ingredients": [
        {
          "name": "qui",
          "amount": 312,
          "id": 62
        },
        {
          "name": "rerum",
          "amount": 803,
          "id": 24
        }
      ],
      "allergens": [
        {
          "name": "rerum",
          "code": 53
        },
        {
          "name": "repellat",
          "code": 47
        },
        {
          "name": "et",
          "code": 82
        }
      ]
    },
    {
      "id": "9335ad4a-1655-4c6e-a2f1-68d1b4479b26",
      "pizzaName": "id",
      "pizzaPrice": 41,
      "ingredients": [
        {
          "name": "recusandae",
          "amount": 252,
          "id": 54
        },
        {
          "name": "non",
          "amount": 178,
          "id": 35
        },
        {
          "name": "tempora",
          "amount": 761,
          "id": 21
        },
        {
          "name": "natus",
          "amount": 452,
          "id": 25
        },
        {
          "name": "aliquid",
          "amount": 723,
          "id": 37
        },
        {
          "name": "sed",
          "amount": 458,
          "id": 49
        }
      ],
      "allergens": [
        {
          "name": "eius",
          "code": 65
        },
        {
          "name": "facilis",
          "code": 97
        }
      ]
    },
    {
      "id": "08eccfba-d779-4f66-a174-f2675cacaaa3",
      "pizzaName": "error",
      "pizzaPrice": 18,
      "ingredients": [
        {
          "name": "dicta",
          "amount": 594,
          "id": 73
        },
        {
          "name": "sed",
          "amount": 100,
          "id": 19
        },
        {
          "name": "voluptatem",
          "amount": 163,
          "id": 68
        },
        {
          "name": "rerum",
          "amount": 152,
          "id": 86
        }
      ],
      "allergens": [
        {
          "name": "sequi",
          "code": 98
        },
        {
          "name": "aut",
          "code": 68
        },
        {
          "name": "error",
          "code": 46
        },
        {
          "name": "velit",
          "code": 91
        },
        {
          "name": "cum",
          "code": 78
        }
      ]
    },
    {
      "id": "7b1c8ff4-76e2-46ef-b2e6-fa892c2bbe53",
      "pizzaName": "aut",
      "pizzaPrice": 29,
      "ingredients": [
        {
          "name": "asperiores",
          "amount": 12,
          "id": 18
        },
        {
          "name": "qui",
          "amount": 312,
          "id": 62
        }
      ],
      "allergens": [
        {
          "name": "quia",
          "code": 63
        },
        {
          "name": "odit",
          "code": 56
        },
        {
          "name": "error",
          "code": 46
        }
      ]
    },
    {
      "id": "6085ff97-cbd0-4cee-8bfe-993cf4f1919c",
      "pizzaName": "fugiat",
      "pizzaPrice": 6,
      "ingredients": [
        {
          "name": "voluptatem",
          "amount": 14,
          "id": 87
        },
        {
          "name": "sint",
          "amount": 203,
          "id": 72
        }
      ],
      "allergens": [
        {
          "name": "nam",
          "code": 41
        },
        {
          "name": "et",
          "code": 24
        },
        {
          "name": "velit",
          "code": 37
        },
        {
          "name": "repudiandae",
          "code": 58
        },
        {
          "name": "aut",
          "code": 19
        }
      ]
    },
    {
      "id": "b18d2fea-dd9b-44b1-9b76-5a887826642a",
      "pizzaName": "consequatur",
      "pizzaPrice": 21,
      "ingredients": [
        {
          "name": "alias",
          "amount": 903,
          "id": 27
        },
        {
          "name": "quidem",
          "amount": 813,
          "id": 91
        }
      ],
      "allergens": [
        {
          "name": "aliquam",
          "code": 4
        },
        {
          "name": "omnis",
          "code": 62
        }
      ]
    },
    {
      "id": "1a7ff5de-a01d-43bf-b342-50b3f45d1c7c",
      "pizzaName": "debitis",
      "pizzaPrice": 21,
      "ingredients": [
        {
          "name": "omnis",
          "amount": 620,
          "id": 15
        },
        {
          "name": "aliquid",
          "amount": 723,
          "id": 37
        },
        {
          "name": "qui",
          "amount": 312,
          "id": 62
        },
        {
          "name": "dolorem",
          "amount": 656,
          "id": 74
        }
      ],
      "allergens": [
        {
          "name": "saepe",
          "code": 81
        },
        {
          "name": "facere",
          "code": 34
        }
      ]
    },
    {
      "id": "9a22cfaa-712c-4c39-8423-a077c860840d",
      "pizzaName": "dolorem",
      "pizzaPrice": 45,
      "ingredients": [
        {
          "name": "sed",
          "amount": 100,
          "id": 19
        },
        {
          "name": "repudiandae",
          "amount": 2,
          "id": 82
        },
        {
          "name": "earum",
          "amount": 895,
          "id": 66
        }
      ],
      "allergens": [
        {
          "name": "dolore",
          "code": 69
        },
        {
          "name": "cum",
          "code": 78
        }
      ]
    },
    {
      "id": "9e58f697-8776-4b55-befc-d689106594ae",
      "pizzaName": "iusto",
      "pizzaPrice": 22,
      "ingredients": [
        {
          "name": "voluptatem",
          "amount": 14,
          "id": 87
        },
        {
          "name": "occaecati",
          "amount": 289,
          "id": 55
        },
        {
          "name": "officia",
          "amount": 251,
          "id": 33
        }
      ],
      "allergens": [
        {
          "name": "laudantium",
          "code": 54
        },
        {
          "name": "odit",
          "code": 64
        },
        {
          "name": "mollitia",
          "code": 40
        },
        {
          "name": "et",
          "code": 66
        }
      ]
    },
    {
      "id": "203c30b3-9225-44b9-8ea6-3e84c018e0d9",
      "pizzaName": "quidem",
      "pizzaPrice": 5,
      "ingredients": [
        {
          "name": "vel",
          "amount": 408,
          "id": 26
        },
        {
          "name": "nulla",
          "amount": 622,
          "id": 13
        },
        {
          "name": "magnam",
          "amount": 184,
          "id": 31
        }
      ],
      "allergens": [
        {
          "name": "et",
          "code": 25
        },
        {
          "name": "voluptatem",
          "code": 55
        }
      ]
    },
    {
      "id": "24da9b0c-b97a-4e00-9782-a895609e59c4",
      "pizzaName": "neque",
      "pizzaPrice": 40,
      "ingredients": [
        {
          "name": "aut",
          "amount": 369,
          "id": 61
        },
        {
          "name": "harum",
          "amount": 997,
          "id": 63
        },
        {
          "name": "vel",
          "amount": 124,
          "id": 43
        }
      ],
      "allergens": [
        {
          "name": "repellat",
          "code": 47
        },
        {
          "name": "voluptas",
          "code": 94
        },
        {
          "name": "expedita",
          "code": 10
        }
      ]
    },
    {
      "id": "ba9c130d-50dc-49a9-94e4-fb4e6afa1be6",
      "pizzaName": "aut",
      "pizzaPrice": 3,
      "ingredients": [
        {
          "name": "aperiam",
          "amount": 690,
          "id": 39
        },
        {
          "name": "odio",
          "amount": 402,
          "id": 59
        },
        {
          "name": "aut",
          "amount": 369,
          "id": 61
        }
      ],
      "allergens": [
        {
          "name": "animi",
          "code": 32
        },
        {
          "name": "facere",
          "code": 34
        },
        {
          "name": "aut",
          "code": 19
        },
        {
          "name": "facilis",
          "code": 97
        }
      ]
    },
    {
      "id": "27407cb9-7225-43db-84b9-1b5246af5d74",
      "pizzaName": "aut",
      "pizzaPrice": 19,
      "ingredients": [
        {
          "name": "eos",
          "amount": 225,
          "id": 96
        },
        {
          "name": "eaque",
          "amount": 291,
          "id": 81
        },
        {
          "name": "est",
          "amount": 534,
          "id": 42
        },
        {
          "name": "quidem",
          "amount": 813,
          "id": 91
        }
      ],
      "allergens": [
        {
          "name": "eius",
          "code": 65
        },
        {
          "name": "laborum",
          "code": 3
        },
        {
          "name": "ipsam",
          "code": 96
        },
        {
          "name": "expedita",
          "code": 10
        }
      ]
    },
    {
      "id": "d3125ec0-ae9d-4ef1-9582-32576ad3cfd7",
      "pizzaName": "nam",
      "pizzaPrice": 20,
      "ingredients": [
        {
          "name": "voluptatum",
          "amount": 3,
          "id": 77
        },
        {
          "name": "est",
          "amount": 534,
          "id": 42
        },
        {
          "name": "maiores",
          "amount": 164,
          "id": 16
        },
        {
          "name": "quidem",
          "amount": 813,
          "id": 91
        },
        {
          "name": "aliquid",
          "amount": 723,
          "id": 37
        },
        {
          "name": "voluptatem",
          "amount": 163,
          "id": 68
        }
      ],
      "allergens": [
        {
          "name": "voluptas",
          "code": 94
        },
        {
          "name": "et",
          "code": 66
        },
        {
          "name": "eum",
          "code": 23
        },
        {
          "name": "iure",
          "code": 30
        }
      ]
    },
    {
      "id": "95403694-23e9-477f-b1a2-8167e8ab8cd4",
      "pizzaName": "et",
      "pizzaPrice": 38,
      "ingredients": [
        {
          "name": "non",
          "amount": 401,
          "id": 64
        },
        {
          "name": "voluptatem",
          "amount": 944,
          "id": 97
        },
        {
          "name": "vel",
          "amount": 369,
          "id": 12
        }
      ],
      "allergens": [
        {
          "name": "dolor",
          "code": 11
        },
        {
          "name": "saepe",
          "code": 81
        },
        {
          "name": "saepe",
          "code": 81
        }
      ]
    },
    {
      "id": "192b923d-be2c-42e4-b619-7dc70323d157",
      "pizzaName": "beatae",
      "pizzaPrice": 7,
      "ingredients": [
        {
          "name": "aperiam",
          "amount": 690,
          "id": 39
        },
        {
          "name": "repudiandae",
          "amount": 2,
          "id": 82
        },
        {
          "name": "et",
          "amount": 134,
          "id": 50
        }
      ],
      "allergens": [
        {
          "name": "explicabo",
          "code": 5
        },
        {
          "name": "est",
          "code": 42
        },
        {
          "name": "repudiandae",
          "code": 95
        }
      ]
    },
    {
      "id": "99ebcf04-aa42-4df4-9b0f-a050609832d1",
      "pizzaName": "sed",
      "pizzaPrice": 37,
      "ingredients": [
        {
          "name": "harum",
          "amount": 997,
          "id": 63
        },
        {
          "name": "nesciunt",
          "amount": 465,
          "id": 75
        },
        {
          "name": "rerum",
          "amount": 152,
          "id": 86
        },
        {
          "name": "nulla",
          "amount": 622,
          "id": 13
        }
      ],
      "allergens": [
        {
          "name": "exercitationem",
          "code": 71
        },
        {
          "name": "quia",
          "code": 21
        },
        {
          "name": "dolore",
          "code": 88
        }
      ]
    },
    {
      "id": "8d5a7606-b286-4f29-98bb-d665347e98ab",
      "pizzaName": "autem",
      "pizzaPrice": 13,
      "ingredients": [
        {
          "name": "eaque",
          "amount": 291,
          "id": 81
        },
        {
          "name": "harum",
          "amount": 997,
          "id": 63
        }
      ],
      "allergens": [
        {
          "name": "cum",
          "code": 78
        },
        {
          "name": "ut",
          "code": 76
        },
        {
          "name": "aut",
          "code": 68
        }
      ]
    },
    {
      "id": "399ab76e-db97-474a-8741-c3c9a2ce087d",
      "pizzaName": "sequi",
      "pizzaPrice": 28,
      "ingredients": [
        {
          "name": "accusamus",
          "amount": 169,
          "id": 3
        },
        {
          "name": "voluptate",
          "amount": 619,
          "id": 53
        },
        {
          "name": "ut",
          "amount": 366,
          "id": 48
        }
      ],
      "allergens": [
        {
          "name": "saepe",
          "code": 22
        },
        {
          "name": "officiis",
          "code": 39
        },
        {
          "name": "qui",
          "code": 14
        }
      ]
    },
    {
      "id": "d2224893-1b7d-45af-b85d-e7b2958dd2c7",
      "pizzaName": "ipsam",
      "pizzaPrice": 0,
      "ingredients": [
        {
          "name": "quae",
          "amount": 438,
          "id": 69
        },
        {
          "name": "distinctio",
          "amount": 663,
          "id": 8
        },
        {
          "name": "earum",
          "amount": 895,
          "id": 66
        }
      ],
      "allergens": [
        {
          "name": "aperiam",
          "code": 99
        },
        {
          "name": "explicabo",
          "code": 5
        }
      ]
    },
    {
      "id": "a33a4cd0-e1df-4b57-b5ef-e2ddab3d8cfa",
      "pizzaName": "ea",
      "pizzaPrice": 47,
      "ingredients": [
        {
          "name": "dolorem",
          "amount": 873,
          "id": 34
        },
        {
          "name": "incidunt",
          "amount": 5,
          "id": 83
        },
        {
          "name": "facilis",
          "amount": 346,
          "id": 0
        },
        {
          "name": "tenetur",
          "amount": 248,
          "id": 70
        }
      ],
      "allergens": [
        {
          "name": "dolor",
          "code": 11
        },
        {
          "name": "et",
          "code": 24
        },
        {
          "name": "fugiat",
          "code": 27
        },
        {
          "name": "nesciunt",
          "code": 93
        },
        {
          "name": "aut",
          "code": 68
        }
      ]
    },
    {
      "id": "4c78fb34-d307-4899-910b-070f32d89ae5",
      "pizzaName": "qui",
      "pizzaPrice": 15,
      "ingredients": [
        {
          "name": "natus",
          "amount": 452,
          "id": 25
        },
        {
          "name": "ex",
          "amount": 405,
          "id": 94
        },
        {
          "name": "aut",
          "amount": 194,
          "id": 65
        }
      ],
      "allergens": [
        {
          "name": "nesciunt",
          "code": 93
        },
        {
          "name": "dolore",
          "code": 88
        },
        {
          "name": "animi",
          "code": 32
        }
      ]
    },
    {
      "id": "f2d8e3ff-7eae-4def-abfe-86e61afefa91",
      "pizzaName": "non",
      "pizzaPrice": 0,
      "ingredients": [
        {
          "name": "sint",
          "amount": 310,
          "id": 4
        },
        {
          "name": "cum",
          "amount": 152,
          "id": 7
        },
        {
          "name": "praesentium",
          "amount": 493,
          "id": 14
        }
      ],
      "allergens": [
        {
          "name": "rerum",
          "code": 8
        },
        {
          "name": "et",
          "code": 25
        },
        {
          "name": "qui",
          "code": 14
        },
        {
          "name": "repellendus",
          "code": 43
        },
        {
          "name": "eius",
          "code": 65
        }
      ]
    },
    {
      "id": "cc802465-d874-4331-9b26-721606a1d3f0",
      "pizzaName": "illo",
      "pizzaPrice": 7,
      "ingredients": [
        {
          "name": "consequatur",
          "amount": 850,
          "id": 95
        },
        {
          "name": "eos",
          "amount": 225,
          "id": 96
        },
        {
          "name": "aut",
          "amount": 816,
          "id": 99
        },
        {
          "name": "rerum",
          "amount": 152,
          "id": 86
        }
      ],
      "allergens": [
        {
          "name": "omnis",
          "code": 62
        },
        {
          "name": "velit",
          "code": 37
        },
        {
          "name": "dolore",
          "code": 69
        }
      ]
    },
    {
      "id": "68e4d6af-6a37-422c-b533-5bccba6edf54",
      "pizzaName": "nulla",
      "pizzaPrice": 21,
      "ingredients": [
        {
          "name": "officiis",
          "amount": 207,
          "id": 47
        },
        {
          "name": "non",
          "amount": 401,
          "id": 64
        },
        {
          "name": "vel",
          "amount": 369,
          "id": 12
        },
        {
          "name": "et",
          "amount": 134,
          "id": 50
        }
      ],
      "allergens": [
        {
          "name": "dolore",
          "code": 48
        },
        {
          "name": "deleniti",
          "code": 7
        },
        {
          "name": "quam",
          "code": 17
        },
        {
          "name": "dolore",
          "code": 88
        }
      ]
    }
  ]
}